cookk/__init__.py
cookk/main.py
cookk-1.4.0.dist-info/METADATA
cookk-1.4.0.dist-info/WHEEL
cookk-1.4.0.dist-info/top_level.txt
cookk-1.4.0.dist-info/RECORD
