Metadata-Version: 2.1
Name: cookk
Version: 1.4.0
Summary: Darkkkk
Home-page: UNKNOWN
Author: Dark
Author-email: wasdark336@gmail.com
License: UNKNOWN
Platform: UNKNOWN
Classifier: Programming Language :: Python :: 3
Classifier: License :: OSI Approved :: MIT License
Classifier: Operating System :: OS Independent
Requires-Python: >=3.10
